aioicloud/__init__.py
aioicloud-0.0.0.dist-info/LICENSE
aioicloud-0.0.0.dist-info/METADATA
aioicloud-0.0.0.dist-info/WHEEL
aioicloud-0.0.0.dist-info/entry_points.txt
aioicloud-0.0.0.dist-info/top_level.txt
aioicloud-0.0.0.dist-info/RECORD
