Metadata-Version: 2.1
Name: aioicloud
Version: 0.0.0
Summary: Python library to ...
Home-page: https://github.com/mandarons/aioicloud
Author: Mandar Patil
Author-email: mandarons@pm.me
Classifier: Programming Language :: Python :: 3
Classifier: Operating System :: OS Independent
Requires-Python: >=3.8
License-File: LICENSE
Requires-Dist: aiohttp[speedups] ==3.*
